<annotation>
	<folder>0</folder>
	<filename>108_right.jpeg</filename>
	<path>D:\DR_Grade_500\0\108_right.jpeg</path>
	<source>
		<database>Unknown</database>
	</source>
	<size>
		<width>3888</width>
		<height>2592</height>
		<depth>3</depth>
	</size>
	<segmented>0</segmented>
	<object>
		<name>OD</name>
		<pose>Unspecified</pose>
		<truncated>0</truncated>
		<difficult>0</difficult>
		<bndbox>
			<xmin>943</xmin>
			<ymin>1057</ymin>
			<xmax>1504</xmax>
			<ymax>1657</ymax>
		</bndbox>
	</object>
	<object>
		<name>Fovea</name>
		<pose>Unspecified</pose>
		<truncated>0</truncated>
		<difficult>0</difficult>
		<bndbox>
			<xmin>2317</xmin>
			<ymin>1105</ymin>
			<xmax>2652</xmax>
			<ymax>1439</ymax>
		</bndbox>
	</object>
</annotation>
